<?xml version="1.0"?>
<WorkflowConfiguration xmlns:xsd="http://www.w3.org/2001/XMLSchema" xmlns:xsi="http://www.w3.org/2001/XMLSchema-instance" xml:space="preserve">
  <Id>fe348767-c2f2-4500-972d-f6e69dd2af01</Id>
  <DisplayName>CloudSync Discover Infrastructure -&gt; UCS Director NetApp &gt;&gt; Post-Discovery</DisplayName>
  <CreatedTime>2016-02-15T20:43:50.5515Z</CreatedTime>
  <ModifiedTime>2016-02-15T20:44:08.7607421Z</ModifiedTime>
  <FirstActivity xsi:type="RootNode">
    <Id>5ecb60ed-bfe3-45ae-852d-d099bcfe0ed0</Id>
    <DisplayName />
    <Children />
  </FirstActivity>
  <ProcessId>383acacd-c4db-475f-92ad-c744c960a487</ProcessId>
</WorkflowConfiguration>